xia_pusher_flask/__init__.py
xia_pusher_flask/api.cpython-39-darwin.so
xia_pusher_flask-0.0.13.dist-info/LICENSE.txt
xia_pusher_flask-0.0.13.dist-info/METADATA
xia_pusher_flask-0.0.13.dist-info/WHEEL
xia_pusher_flask-0.0.13.dist-info/top_level.txt
xia_pusher_flask-0.0.13.dist-info/RECORD
