Metadata-Version: 2.1
Name: xia-pusher-flask
Version: 0.0.13
Summary: UNKNOWN
Home-page: https://develop.x-i-a.com/docs/xia-pusher-flask/0.0.13/index.html
Author: X-I-A
Author-email: admin@x-i-a.com
License: UNKNOWN
Platform: UNKNOWN
Requires-Python: >=3.9
License-File: LICENSE.txt
Requires-Dist: flask
Requires-Dist: xia-pusher
Requires-Dist: xia-agent-flask
